pycudadecon/__init__.py
pycudadecon/_ctyped.py
pycudadecon/_libwrap.py
pycudadecon/affine.py
pycudadecon/camcor.py
pycudadecon/deconvolution.py
pycudadecon/napari.py
pycudadecon/napari.yaml
pycudadecon/otf.py
pycudadecon/util.py
pycudadecon-0.5.1.dist-info/METADATA
pycudadecon-0.5.1.dist-info/WHEEL
pycudadecon-0.5.1.dist-info/entry_points.txt
pycudadecon-0.5.1.dist-info/licenses/LICENSE
pycudadecon-0.5.1.dist-info/RECORD
