Metadata-Version: 2.3
Name: pycudadecon
Version: 0.5.1
Summary: Python wrapper for CUDA-accelerated 3D deconvolution
Project-URL: Documentation, https://tlambert03.github.io/pycudadecon/
Project-URL: Source, https://github.com/tlambert03/pycudadecon
Project-URL: Tracker, https://github.com/tlambert03/pycudadecon/issues
Author-email: Talley Lambert <talley.lambert@gmail.com>
License: MIT
License-File: LICENSE
Keywords: CUDA,deconvolution,microscopy
Classifier: Development Status :: 4 - Beta
Classifier: Environment :: GPU :: NVIDIA CUDA
Classifier: Framework :: napari
Classifier: Intended Audience :: Science/Research
Classifier: License :: OSI Approved :: MIT License
Classifier: Programming Language :: Python :: 3
Classifier: Programming Language :: Python :: 3.8
Classifier: Programming Language :: Python :: 3.9
Classifier: Programming Language :: Python :: 3.10
Classifier: Programming Language :: Python :: 3.11
Classifier: Programming Language :: Python :: 3.12
Classifier: Topic :: Scientific/Engineering
Requires-Python: >=3.8
Requires-Dist: numpy
Requires-Dist: tifffile
Requires-Dist: typing-extensions
Provides-Extra: dev
Requires-Dist: ipython; extra == 'dev'
Requires-Dist: mypy; extra == 'dev'
Requires-Dist: pdbpp; extra == 'dev'
Requires-Dist: pre-commit; extra == 'dev'
Requires-Dist: rich; extra == 'dev'
Requires-Dist: ruff; extra == 'dev'
Provides-Extra: docs
Requires-Dist: furo==2022.9.29; extra == 'docs'
Requires-Dist: ghp-import==2.1.0; extra == 'docs'
Requires-Dist: jupyter-book==0.13.1; extra == 'docs'
Requires-Dist: sphinx-autodoc-typehints==1.19.1; extra == 'docs'
Provides-Extra: test
Requires-Dist: pytest-cov; extra == 'test'
Requires-Dist: pytest>=6.0; extra == 'test'
